my_wish.py
my_wish-1.0.0.dist-info/METADATA
my_wish-1.0.0.dist-info/WHEEL
my_wish-1.0.0.dist-info/entry_points.txt
my_wish-1.0.0.dist-info/top_level.txt
my_wish-1.0.0.dist-info/RECORD
