Metadata-Version: 2.2
Name: my_wish
Version: 1.0.0
Requires-Dist: rich
Dynamic: requires-dist
